{"GlobalPropertiesHash":"Bh6ZYOCYuluOnHCw4QW6Dp6gy+UIJODyunyomhKWa68=","FingerprintPatternsHash":"gq3WsqcKBUGTSNle7RKKyXRIwh7M8ccEqOqYvIzoM04=","PropertyOverridesHash":"8ZRc1sGeVrPBx4lD717BgRaQekyh78QKV9SKsdt638U=","InputHashes":["lzIFNlDF2G2sGG12lKGYKb4rUr/XnazopwLkXsHFt5s=","\u002B26Yuwux9kd0xvFzZWA2tKfm5d\u002BgXWmCHrtYHl\u002BUzAM=","ISIoPcjUZqUaE9xVyB62\u002B8ulM8iafxyoN9YPLtbAXwI=","eHq1Hlrm1gHPQvLowLJvkB/QIplZxw46XtX3HWn49Io=","qqNdicA4lFvroiq\u002BywFrrSczebg2zSrraPiCXchFDWM=","Tmsyx8bOmOsV75yBWp/QKq/Smi1ZgzzS0MC1vC60EzU=","G/rrFjFfs2RRrLbb6ZutlITZYyFO3KDQWzioD6dfzSQ=","iitOZ\u002BKi0DKzF/6ooVVoq8TMyOuGNeXEVX8GaLPkzWY=","oPzsKtevJ0Figzms5JSW6R9dlPlBVdc\u002BG/jM/SUrzAE=","zLjAf6tTuTEoCHZwTGVNz2I70d42ALlsvQgV3Nv37yc=","qymtSMygCIUn1OESBSlE\u002BtnTNLMRnPEYDCUAizd4H7g=","qSJxejpIcc/jc5Js00wtAAsmgkZERTR8o1K8ubEWzv0=","gnyeHErbUK3AbKh2pWz0rTon6yPASb1\u002BDB/hmBvb8jM=","TRtfbH4wEOxNDOXG/qMTpRxP\u002BSnGV3PD3itTXAMkD\u002BY=","O55mflCt6tslNsutBx1bwJ98jhwlAhvCb0va\u002Bkct9L0=","6Sflie8WUFY9BvRwp\u002Bajoaeq3cLAnWAETfxMKhtobjY=","5N0Us0Wdwy/09WT6M0Tq7UvsRIZ/6SyO1NvTPgM/uak=","24bNtKnW25ndF78Hwoq7krox7zhSlF5oq5Lhv1bVSF0="],"CachedAssets":{"lzIFNlDF2G2sGG12lKGYKb4rUr/XnazopwLkXsHFt5s=":{"Identity":"C:\\Users\\isaac\\Downloads\\Renta de Departamentos Web\\RentaDepartamentosWeb\\RentaDepartamentosWeb\\wwwroot\\css\\site.css","SourceId":"RentaDepartamentosWeb","SourceType":"Discovered","ContentRoot":"C:\\Users\\isaac\\Downloads\\Renta de Departamentos Web\\RentaDepartamentosWeb\\RentaDepartamentosWeb\\wwwroot\\","BasePath":"/","RelativePath":"css/site#[.{fingerprint}]?.css","AssetKind":"All","AssetMode":"All","AssetRole":"Primary","AssetMergeBehavior":null,"AssetMergeSource":"","RelatedAsset":null,"AssetTraitName":null,"AssetTraitValue":null,"Fingerprint":"bkqetmtghd","Integrity":"BV0mGrTrUPmPp0sXNWmww60pe4/8ZQXnkiVONTxEeeE=","CopyToOutputDirectory":"Never","CopyToPublishDirectory":"PreserveNewest","OriginalItemSpec":"wwwroot\\css\\site.css","FileLength":26994,"LastWriteTime":"2026-06-30T20:21:05.6184598+00:00"},"\u002B26Yuwux9kd0xvFzZWA2tKfm5d\u002BgXWmCHrtYHl\u002BUzAM=":{"Identity":"C:\\Users\\isaac\\Downloads\\Renta de Departamentos Web\\RentaDepartamentosWeb\\RentaDepartamentosWeb\\wwwroot\\js\\site.js","SourceId":"RentaDepartamentosWeb","SourceType":"Discovered","ContentRoot":"C:\\Users\\isaac\\Downloads\\Renta de Departamentos Web\\RentaDepartamentosWeb\\RentaDepartamentosWeb\\wwwroot\\","BasePath":"/","RelativePath":"js/site#[.{fingerprint}]?.js","AssetKind":"All","AssetMode":"All","AssetRole":"Primary","AssetMergeBehavior":null,"AssetMergeSource":"","RelatedAsset":null,"AssetTraitName":null,"AssetTraitValue":null,"Fingerprint":"53ay39tiu2","Integrity":"kV7AfLUkdrsyNMdN/rRDmsvZxOKBx93blpR9SDdqqlc=","CopyToOutputDirectory":"Never","CopyToPublishDirectory":"PreserveNewest","OriginalItemSpec":"wwwroot\\js\\site.js","FileLength":1552,"LastWriteTime":"2026-06-30T20:21:17.6599629+00:00"}},"CachedCopyCandidates":{}}